{
  "id": "2886222",
  "name": "小U课堂-移动端",
  "font_family": "iconfont",
  "css_prefix_text": "icon-",
  "description": "",
  "glyphs": [
    {
      "icon_id": "1183130",
      "name": "定位",
      "font_class": "dingwei",
      "unicode": "e675",
      "unicode_decimal": 58997
    },
    {
      "icon_id": "2076312",
      "name": " 我的",
      "font_class": "wode",
      "unicode": "e8a0",
      "unicode_decimal": 59552
    },
    {
      "icon_id": "8530347",
      "name": "搜索 ",
      "font_class": "sousuo",
      "unicode": "e60d",
      "unicode_decimal": 58893
    },
    {
      "icon_id": "13332684",
      "name": "商城",
      "font_class": "shangcheng",
      "unicode": "e60c",
      "unicode_decimal": 58892
    }
  ]
}
